django_admin_reversefields/__init__.py
django_admin_reversefields/mixins.py
django_admin_reversefields-0.1.0.dist-info/METADATA
django_admin_reversefields-0.1.0.dist-info/WHEEL
django_admin_reversefields-0.1.0.dist-info/licenses/LICENSE
django_admin_reversefields-0.1.0.dist-info/RECORD
