Metadata-Version: 2.4
Name: django-admin-reversefields
Version: 0.1.0
Summary: A Django mixin for easily including reverse relationships in your changeforms in the admin
Project-URL: Homepage, https://github.com/tnware/django-admin-reversefields
Project-URL: Repository, https://github.com/tnware/django-admin-reversefields
Project-URL: Documentation, https://tnware.github.io/django-admin-reversefields
Author-email: Tyler Woods <tyler@tylermade.net>
Maintainer-email: Tyler Woods <tyler@tylermade.net>
License-Expression: BSD-2-Clause
License-File: LICENSE
Keywords: admin,django,mixin,relationship,reverse
Classifier: Development Status :: 4 - Beta
Classifier: Environment :: Web Environment
Classifier: Framework :: Django :: 4.2
Classifier: Framework :: Django :: 5.0
Classifier: Framework :: Django :: 5.1
Classifier: Framework :: Django :: 5.2
Classifier: Intended Audience :: Developers
Classifier: License :: OSI Approved :: BSD License
Classifier: Operating System :: OS Independent
Classifier: Programming Language :: Python
Classifier: Programming Language :: Python :: 3
Classifier: Programming Language :: Python :: 3 :: Only
Classifier: Programming Language :: Python :: 3.10
Classifier: Programming Language :: Python :: 3.11
Classifier: Programming Language :: Python :: 3.12
Classifier: Programming Language :: Python :: 3.13
Classifier: Topic :: Internet :: WWW/HTTP
Classifier: Topic :: Internet :: WWW/HTTP :: Dynamic Content
Classifier: Topic :: Internet :: WWW/HTTP :: WSGI
Classifier: Topic :: Software Development :: Libraries :: Application Frameworks
Classifier: Topic :: Software Development :: Libraries :: Python Modules
Requires-Python: >=3.10
Requires-Dist: django>=4.2
